tests/__init__.py
tests/conftest.py
tests/test_decorators.py
timeguardian/__init__.py
timeguardian/decorators.py
timeguardian/logging_conf.py
timeguardian-0.0.7.dist-info/LICENSE
timeguardian-0.0.7.dist-info/METADATA
timeguardian-0.0.7.dist-info/WHEEL
timeguardian-0.0.7.dist-info/top_level.txt
timeguardian-0.0.7.dist-info/RECORD
