Metadata-Version: 2.1
Name: timeguardian
Version: 0.0.7
Summary: TimeGuardian is a package for execution time measurement
Home-page: https://github.com/ceboaldin/TimeGuardian
Author: Aldin Cebo
Author-email: ceboaldin@gmail.com
Classifier: Programming Language :: Python :: 3
Classifier: License :: OSI Approved :: MIT License
Classifier: Operating System :: OS Independent
License-File: LICENSE
Requires-Dist: rich
Requires-Dist: psutil
